crowdsec_tracker_api/__init__.py
crowdsec_tracker_api/base_model.py
crowdsec_tracker_api/http_client.py
crowdsec_tracker_api/models.py
crowdsec_tracker_api/services/__init__.py
crowdsec_tracker_api/services/cves.py
crowdsec_tracker_api/services/integrations.py
crowdsec_tracker_api-1.102.3.dist-info/licenses/LICENSE
crowdsec_tracker_api-1.102.3.dist-info/METADATA
crowdsec_tracker_api-1.102.3.dist-info/WHEEL
crowdsec_tracker_api-1.102.3.dist-info/top_level.txt
crowdsec_tracker_api-1.102.3.dist-info/RECORD
