Metadata-Version: 2.4
Name: crowdsec_tracker_api
Version: 1.102.3
Summary: This is the API to manage Crowdsec Live Exploit Tracker service
Author-email: crowdsec <info@crowdsec.net>
License: MIT
Requires-Python: >=3.11
License-File: LICENSE
Requires-Dist: httpx==0.27.0
Requires-Dist: botocore
Requires-Dist: pydantic[email,timezone]<3.0.0,>=2.5.0
Dynamic: license-file
